Metadata-Version: 2.1
Name: licplot
Version: 1.0.5
Summary: LIC plotting algorithm.
Home-page: https://github.com/alexus37/licplot
Maintainer: Alexander Lelidis
Maintainer-email: alex.lexus.info@gmail.com
License: BSD
Download-URL: https://pypi.org/project/licplot
Platform: UNKNOWN
Requires-Python: >=3.0
